MANIFEST.in
README.rst
setup.cfg
setup.py
docs/CONTRIBUTORS.txt
docs/HISTORY.txt
docs/INSTALL.txt
docs/LICENSE.txt
hl/__init__.py
hl.pas.samlplugin.egg-info/PKG-INFO
hl.pas.samlplugin.egg-info/SOURCES.txt
hl.pas.samlplugin.egg-info/dependency_links.txt
hl.pas.samlplugin.egg-info/entry_points.txt
hl.pas.samlplugin.egg-info/namespace_packages.txt
hl.pas.samlplugin.egg-info/not-zip-safe
hl.pas.samlplugin.egg-info/requires.txt
hl.pas.samlplugin.egg-info/top_level.txt
hl/pas/__init__.py
hl/pas/samlplugin/__init__.py
hl/pas/samlplugin/client.py
hl/pas/samlplugin/configure.zcml
hl/pas/samlplugin/install.py
hl/pas/samlplugin/interfaces.py
hl/pas/samlplugin/plugin.py
hl/pas/samlplugin/util.py
hl/pas/samlplugin/browser/__init__.py
hl/pas/samlplugin/browser/add_plugin.pt
hl/pas/samlplugin/browser/configure.zcml
hl/pas/samlplugin/browser/icon.gif
hl/pas/samlplugin/browser/views.py
hl/pas/samlplugin/profiles/default/skins.xml
hl/pas/samlplugin/saml2/__init__.py
hl/pas/samlplugin/saml2/assertion.py
hl/pas/samlplugin/saml2/attribute_converter.py
hl/pas/samlplugin/saml2/attribute_resolver.py
hl/pas/samlplugin/saml2/authn.py
hl/pas/samlplugin/saml2/cache.py
hl/pas/samlplugin/saml2/cipher.py
hl/pas/samlplugin/saml2/client.py
hl/pas/samlplugin/saml2/client_base.py
hl/pas/samlplugin/saml2/config.py
hl/pas/samlplugin/saml2/discovery.py
hl/pas/samlplugin/saml2/ecp.py
hl/pas/samlplugin/saml2/ecp_client.py
hl/pas/samlplugin/saml2/entity.py
hl/pas/samlplugin/saml2/eptid.py
hl/pas/samlplugin/saml2/httpbase.py
hl/pas/samlplugin/saml2/httputil.py
hl/pas/samlplugin/saml2/ident.py
hl/pas/samlplugin/saml2/mcache.py
hl/pas/samlplugin/saml2/md.py
hl/pas/samlplugin/saml2/mdbcache.py
hl/pas/samlplugin/saml2/mdie.py
hl/pas/samlplugin/saml2/mdstore.py
hl/pas/samlplugin/saml2/metadata.py
hl/pas/samlplugin/saml2/mongo_store.py
hl/pas/samlplugin/saml2/pack.py
hl/pas/samlplugin/saml2/population.py
hl/pas/samlplugin/saml2/request.py
hl/pas/samlplugin/saml2/response.py
hl/pas/samlplugin/saml2/s_utils.py
hl/pas/samlplugin/saml2/saml.py
hl/pas/samlplugin/saml2/samlp.py
hl/pas/samlplugin/saml2/sdb.py
hl/pas/samlplugin/saml2/server.py
hl/pas/samlplugin/saml2/sigver.py
hl/pas/samlplugin/saml2/soap.py
hl/pas/samlplugin/saml2/time_util.py
hl/pas/samlplugin/saml2/validate.py
hl/pas/samlplugin/saml2/virtual_org.py
