Metadata-Version: 1.1
Name: hl.pas.samlplugin
Version: 1.3
Summary: SAML2 authentication for Zope
Home-page: https://github.com/Haufe-Lexware/hl.pas.samlplugin
Author: Thomas Schorr
Author-email: thomas.schorr@haufe-lexware.com
License: Apache 2.0
Keywords: saml2 zope pas
Platform: UNKNOWN
Classifier: Framework :: Zope2
Classifier: Intended Audience :: Developers
Classifier: License :: OSI Approved :: Apache Software License
